ghostpath/__init__.py
ghostpath/main.py
ghostpath/version.py
ghostpath/data/__init__.py
ghostpath/data/path-wordlist.txt
ghostpath/data/subdomain-wordlist.txt
ghostpath/data/web-path-wordlist.txt
ghostpath/modules/__init__.py
ghostpath/modules/active/__init__.py
ghostpath/modules/active/domainscope.py
ghostpath/modules/active/pathprobe.py
ghostpath/modules/passive/__init__.py
ghostpath/modules/passive/certtrack.py
ghostpath/modules/passive/timetrail.py
ghostpath/modules/shared/__init__.py
ghostpath/modules/shared/logger.py
ghostpath/modules/shared/output.py
ghostpath-2.3.7.dist-info/licenses/LICENSE
ghostpath-2.3.7.dist-info/METADATA
ghostpath-2.3.7.dist-info/WHEEL
ghostpath-2.3.7.dist-info/entry_points.txt
ghostpath-2.3.7.dist-info/top_level.txt
ghostpath-2.3.7.dist-info/RECORD
