Metadata-Version: 2.4
Name: GhostPath
Version: 2.3.7
Summary: GhostPath - Interactive Recon Shell for Ethical Hackers
Home-page: https://github.com/atharvbyadav/GhostPath
Author: Atharv Yadav
License: BSD-3-Clause
Project-URL: Documentation, https://github.com/atharvbyadav/GhostPath
Project-URL: Source, https://github.com/atharvbyadav/GhostPath
Project-URL: Tracker, https://github.com/atharvbyadav/GhostPath/issues
Keywords: osint,recon,security,hacking,penetration-testing,cli
Classifier: Programming Language :: Python :: 3
Classifier: Environment :: Console
Classifier: Intended Audience :: Developers
Classifier: Topic :: Security
Classifier: License :: OSI Approved :: BSD License
Requires-Python: >=3.7
License-File: LICENSE
Requires-Dist: requests>=2.31.0
Requires-Dist: colorama>=0.4.6
Dynamic: author
Dynamic: classifier
Dynamic: description
Dynamic: description-content-type
Dynamic: home-page
Dynamic: keywords
Dynamic: license
Dynamic: license-file
Dynamic: project-url
Dynamic: requires-dist
Dynamic: requires-python
Dynamic: summary
